{"431021822448762880":{"name":"SibbeeeGold","gold":320,"banks":216,"prays":3354,"totalLosses":11367,"prayTotal":176020,"totalWinnings":10308,"failedPrayers":2930},"596336855729831976":{"name":"Sebbe","gold":1680,"banks":120,"prays":191,"totalLosses":14525,"prayTotal":7401,"totalWinnings":8000,"failedPrayers":123},"196272863148376064":{"name":"Ozzcarr","gold":848,"banks":115,"totalLosses":6534,"prays":1884,"prayTotal":89800,"failedPrayers":1609,"totalWinnings":1200},"286153078116450304":{"name":"Heroz","gold":1638,"banks":13,"prays":286,"totalLosses":28639,"prayTotal":16300,"failedPrayers":112,"totalWinnings":null},"289102730046472192":{"name":"KuBis","gold":40,"banks":14,"prays":147,"totalLosses":1100,"prayTotal":12084,"totalWinnings":0,"failedPrayers":122},"277545581390462986":{"name":"Jag är vem","gold":0,"banks":2,"prays":13,"totalLosses":2600,"prayTotal":600,"totalWinnings":6000,"failedPrayers":11},"97358784006983680":{"name":"Vaktmaestarn","gold":434,"banks":1,"prays":0,"totalLosses":0,"prayTotal":0,"failedPrayers":0},"293674457971818496":{"name":"Fluffzzz","gold":1250,"banks":0,"prays":3,"totalLosses":250,"prayTotal":500,"totalWinnings":0,"failedPrayers":2},"227112639610748939":{"name":"Mikty","gold":1000,"banks":0,"prays":1,"totalLosses":100,"prayTotal":100,"totalWinnings":0,"failedPrayers":0},"302762463806488576":{"name":"Cedian","gold":900,"banks":0,"prays":0,"totalLosses":100,"prayTotal":0,"totalWinnings":0,"failedPrayers":0},"261529891688808456":{"name":"Mariohrst","gold":100,"banks":0,"prays":9,"totalLosses":1400,"prayTotal":500,"totalWinnings":0,"failedPrayers":6}}